GenWoYiqiXieMakefile/README.md
GenWoYiqiXieMakefile/__init__.py
GenWoYiqiXieMakefile/__main__.py
GenWoYiqiXieMakefile/file.epub
GenWoYiqiXieMakefile/index.html
GenWoYiqiXieMakefile/css/__init__.py
GenWoYiqiXieMakefile/css/annotations.css
GenWoYiqiXieMakefile/css/main.css
GenWoYiqiXieMakefile/css/normalize.css
GenWoYiqiXieMakefile/css/popup.css
GenWoYiqiXieMakefile/font/__init__.py
GenWoYiqiXieMakefile/font/fontello.eot
GenWoYiqiXieMakefile/font/fontello.svg
GenWoYiqiXieMakefile/font/fontello.ttf
GenWoYiqiXieMakefile/font/fontello.woff
GenWoYiqiXieMakefile/img/__init__.py
GenWoYiqiXieMakefile/img/annotator-glyph-sprite.png
GenWoYiqiXieMakefile/img/annotator-icon-sprite.png
GenWoYiqiXieMakefile/img/apple-touch-icon.png
GenWoYiqiXieMakefile/img/cancelfullscreen.png
GenWoYiqiXieMakefile/img/close.png
GenWoYiqiXieMakefile/img/fullscreen.png
GenWoYiqiXieMakefile/img/loader.gif
GenWoYiqiXieMakefile/img/menu-icon.png
GenWoYiqiXieMakefile/img/save.png
GenWoYiqiXieMakefile/img/saved.png
GenWoYiqiXieMakefile/img/settings-s.png
GenWoYiqiXieMakefile/img/settings.png
GenWoYiqiXieMakefile/img/star.png
GenWoYiqiXieMakefile/js/__init__.py
GenWoYiqiXieMakefile/js/epub.js
GenWoYiqiXieMakefile/js/epub.min.js
GenWoYiqiXieMakefile/js/epub.min.map
GenWoYiqiXieMakefile/js/hooks.min.js
GenWoYiqiXieMakefile/js/hooks.min.map
GenWoYiqiXieMakefile/js/reader.js
GenWoYiqiXieMakefile/js/reader.js.map
GenWoYiqiXieMakefile/js/reader.min.js
GenWoYiqiXieMakefile/js/reader.min.map
GenWoYiqiXieMakefile/js/hooks/__init__.py
GenWoYiqiXieMakefile/js/hooks/extensions/__init__.py
GenWoYiqiXieMakefile/js/hooks/extensions/highlight.js
GenWoYiqiXieMakefile/js/libs/__init__.py
GenWoYiqiXieMakefile/js/libs/jquery.min.js
GenWoYiqiXieMakefile/js/libs/localforage.min.js
GenWoYiqiXieMakefile/js/libs/screenfull.js
GenWoYiqiXieMakefile/js/libs/screenfull.min.js
GenWoYiqiXieMakefile/js/libs/zip.min.js
GenWoYiqiXieMakefile/js/plugins/__init__.py
GenWoYiqiXieMakefile/js/plugins/hypothesis.js
gen_wo_yiqi_xie_makefile-2024.3.2.0.dist-info/METADATA
gen_wo_yiqi_xie_makefile-2024.3.2.0.dist-info/WHEEL
gen_wo_yiqi_xie_makefile-2024.3.2.0.dist-info/entry_points.txt
gen_wo_yiqi_xie_makefile-2024.3.2.0.dist-info/top_level.txt
gen_wo_yiqi_xie_makefile-2024.3.2.0.dist-info/RECORD
